known_problems_fastapi_router/__init__.py
known_problems_fastapi_router/exception_handlers.py
known_problems_fastapi_router/py.typed
known_problems_fastapi_router/routing.py
known_problems_fastapi_router/types.py
known_problems_fastapi_router-0.111.0.dist-info/LICENSE.txt
known_problems_fastapi_router-0.111.0.dist-info/METADATA
known_problems_fastapi_router-0.111.0.dist-info/WHEEL
known_problems_fastapi_router-0.111.0.dist-info/RECORD
