Metadata-Version: 2.1
Name: known-problems-fastapi-router
Version: 0.111.0
Summary: A known problem API router package
License: MIT
Author: Fabian Haenel
Author-email: fabian.haenel@fastlane.net
Requires-Python: >=3.10,<4.0
Classifier: License :: OSI Approved :: MIT License
Classifier: Programming Language :: Python :: 3
Classifier: Programming Language :: Python :: 3.10
Classifier: Programming Language :: Python :: 3.11
Classifier: Programming Language :: Python :: 3.12
Requires-Dist: fastapi (==0.111)
Requires-Dist: pydantic (>=2.3,<3)
